recallrai/__init__.py
recallrai/async_client.py
recallrai/async_merge_conflict.py
recallrai/async_session.py
recallrai/async_user.py
recallrai/client.py
recallrai/exceptions/__init__.py
recallrai/exceptions/auth.py
recallrai/exceptions/base.py
recallrai/exceptions/merge_conflicts.py
recallrai/exceptions/network.py
recallrai/exceptions/server.py
recallrai/exceptions/sessions.py
recallrai/exceptions/users.py
recallrai/exceptions/validation.py
recallrai/merge_conflict.py
recallrai/models/__init__.py
recallrai/models/merge_conflict.py
recallrai/models/session.py
recallrai/models/user.py
recallrai/session.py
recallrai/user.py
recallrai/utils/__init__.py
recallrai/utils/async_http_client.py
recallrai/utils/http_client.py
recallrai-0.5.8.dist-info/METADATA
recallrai-0.5.8.dist-info/WHEEL
recallrai-0.5.8.dist-info/RECORD
