Metadata-Version: 2.4
Name: recallrai
Version: 0.5.8
Summary: Official Python SDK for RecallrAI - Revolutionary contextual memory system that enables AI assistants to form meaningful connections between conversations, just like human memory.
License: MIT
Keywords: ai,memory,context,llm,mem0,getzep,zep
Author: Devasheesh Mishra
Author-email: devasheesh@recallrai.com
Requires-Python: >=3.9,<3.15
Classifier: Intended Audience :: Developers
Classifier: License :: OSI Approved :: MIT License
Classifier: Operating System :: OS Independent
Classifier: Programming Language :: Python :: 3
Classifier: Programming Language :: Python :: 3.9
Classifier: Programming Language :: Python :: 3.10
Classifier: Programming Language :: Python :: 3.11
Classifier: Programming Language :: Python :: 3.12
Classifier: Programming Language :: Python :: 3.13
Classifier: Programming Language :: Python :: 3.14
Requires-Dist: httpx (>=0.28.1,<0.29.0)
Requires-Dist: pydantic (>=2.11.1,<3.0.0)
Project-URL: Homepage, https://recallrai.com
Project-URL: Repository, https://github.com/recallrai/sdk-python
